pybabyfpa/__init__.py
pybabyfpa-0.0.7.dist-info/LICENSE
pybabyfpa-0.0.7.dist-info/METADATA
pybabyfpa-0.0.7.dist-info/WHEEL
pybabyfpa-0.0.7.dist-info/top_level.txt
pybabyfpa-0.0.7.dist-info/RECORD
