Metadata-Version: 2.2
Name: pybabyfpa
Version: 0.0.7
Summary: "This package can be used to control the Baby Brezza's Formula Pro Advanced WiFi."
Home-page: https://github.com/joncar/pybabyfpa
Author: Jon Caruana
Author-email: jon@joncaruana.com
Classifier: Programming Language :: Python :: 3
Classifier: License :: OSI Approved :: MIT License
Classifier: Operating System :: OS Independent
Requires-Python: >=3.6
License-File: LICENSE
